bit_manipulation/__init__.py
bit_manipulation/isolate_last_bit.py
data_structure/__init__.py
data_structure/array/__init__.py
data_structure/array/sparse_table.py
data_structure/tree/__init__.py
data_structure/tree/binary_indexed_tree.py
pychampion-0.1.0.dist-info/METADATA
pychampion-0.1.0.dist-info/WHEEL
pychampion-0.1.0.dist-info/top_level.txt
pychampion-0.1.0.dist-info/RECORD
