Metadata-Version: 2.4
Name: pychampion
Version: 0.1.0
Summary: Add your description here
Requires-Python: >=3.13
Requires-Dist: isort>=6.0.1
Requires-Dist: pre-commit>=4.2.0
Requires-Dist: pytest>=8.4.1
Requires-Dist: ruff>=0.12.1
